roboto_sdk/__init__.py
roboto_sdk/auth/__init__.py
roboto_sdk/auth/pat.py
roboto_sdk/auth/permissions.py
roboto_sdk/cli/__init__.py
roboto_sdk/cli/actions/__init__.py
roboto_sdk/cli/actions/commands.py
roboto_sdk/cli/actions/create.py
roboto_sdk/cli/actions/delete.py
roboto_sdk/cli/actions/invoke.py
roboto_sdk/cli/actions/list_invocations.py
roboto_sdk/cli/actions/search.py
roboto_sdk/cli/actions/show.py
roboto_sdk/cli/actions/update.py
roboto_sdk/cli/argparse.py
roboto_sdk/cli/command/__init__.py
roboto_sdk/cli/command/args.py
roboto_sdk/cli/command/model.py
roboto_sdk/cli/common_args/__init__.py
roboto_sdk/cli/common_args/actions.py
roboto_sdk/cli/common_args/exceptions.py
roboto_sdk/cli/common_args/orgs.py
roboto_sdk/cli/config.py
roboto_sdk/cli/context.py
roboto_sdk/cli/datasets/__init__.py
roboto_sdk/cli/datasets/commands.py
roboto_sdk/cli/datasets/create.py
roboto_sdk/cli/datasets/delete_dataset.py
roboto_sdk/cli/datasets/delete_files.py
roboto_sdk/cli/datasets/download_files.py
roboto_sdk/cli/datasets/list_files.py
roboto_sdk/cli/datasets/search.py
roboto_sdk/cli/datasets/shared_helpdoc.py
roboto_sdk/cli/datasets/show.py
roboto_sdk/cli/datasets/update.py
roboto_sdk/cli/datasets/upload_files.py
roboto_sdk/cli/entry.py
roboto_sdk/cli/extension/__init__.py
roboto_sdk/cli/extension/cli_extension.py
roboto_sdk/cli/images/__init__.py
roboto_sdk/cli/images/commands.py
roboto_sdk/cli/images/delete_image.py
roboto_sdk/cli/images/delete_repo.py
roboto_sdk/cli/images/list_images.py
roboto_sdk/cli/images/list_repos.py
roboto_sdk/cli/images/login.py
roboto_sdk/cli/images/pull.py
roboto_sdk/cli/images/push.py
roboto_sdk/cli/invocations/__init__.py
roboto_sdk/cli/invocations/logs.py
roboto_sdk/cli/invocations/show.py
roboto_sdk/cli/invocations/status.py
roboto_sdk/cli/orgs/__init__.py
roboto_sdk/cli/orgs/commands.py
roboto_sdk/cli/tokens/__init__.py
roboto_sdk/cli/tokens/commands.py
roboto_sdk/cli/triggers/__init__.py
roboto_sdk/cli/triggers/commands.py
roboto_sdk-0.1.36.dist-info/METADATA
roboto_sdk-0.1.36.dist-info/WHEEL
roboto_sdk-0.1.36.dist-info/entry_points.txt
roboto_sdk-0.1.36.dist-info/RECORD
