Metadata-Version: 2.1
Name: roboto-sdk
Version: 0.1.36
Summary: Tools for interacting with roboto.ai
License: MIT
Author: Roboto
Author-email: admin@roboto.ai
Requires-Python: >=3.9,<4.0
Classifier: License :: OSI Approved :: MIT License
Classifier: Programming Language :: Python :: 3
Classifier: Programming Language :: Python :: 3.9
Classifier: Programming Language :: Python :: 3.10
Classifier: Programming Language :: Python :: 3.11
Requires-Dist: boto3[crt] (>=1.26,<1.27)
Requires-Dist: pathspec (>=0.11,<0.12)
Requires-Dist: pydantic (>=1.10,<1.11)
Requires-Dist: pyjwt (>=2.7,<2.8)
Requires-Dist: tenacity (>=8.2,<8.3)
Requires-Dist: tqdm (>=4.65,<4.66)
Requires-Dist: typing-extensions (>=4.8,<4.9) ; python_version < "3.10"
